qsea/__init__ (1).py
qsea/__init__.py
qsea/qsea dev test.py
qsea/qsea test.py
qsea/test2.py
qsea/tools.py
qsea-1.0.0.dist-info/LICENSE.txt
qsea-1.0.0.dist-info/METADATA
qsea-1.0.0.dist-info/PKG-INFO (1)
qsea-1.0.0.dist-info/WHEEL
qsea-1.0.0.dist-info/top_level.txt
qsea-1.0.0.dist-info/RECORD
