Metadata-Version: 2.1
Name: qsea
Version: 1.0.0
Summary: Convenient way to work with Qlik Sense Engine API from Python
Home-page: https://github.com/ncthuc/qsea
Download-URL: https://pypi.org/project/qsea/
Author: Lev Biriukov
Author-email: lbiryukov@gmail.com
License: MIT
Keywords: QlikSense,Qlik
License-File: LICENSE.txt
Requires-Dist: pandas
Requires-Dist: datetime
Requires-Dist: websocket-client
